AUTHORS
LICENSE
MANIFEST.in
README.rst
setup.py
django_sentrylogs.egg-info/PKG-INFO
django_sentrylogs.egg-info/SOURCES.txt
django_sentrylogs.egg-info/dependency_links.txt
django_sentrylogs.egg-info/not-zip-safe
django_sentrylogs.egg-info/requires.txt
django_sentrylogs.egg-info/top_level.txt
djsentrylogs/__init__.py
djsentrylogs/models.py
djsentrylogs/management/__init__.py
djsentrylogs/management/commands/__init__.py
djsentrylogs/management/commands/process_logs.py